similarity/__init__.py
similarity/__main__.py
similarity/df_style.css
similarity/similarity_cmd.py
similarity/similarity_io.py
similarity/similarity_logging.py
similarity/similarity_ui.py
similarity_processor-0.1.5.dist-info/LICENSE.md
similarity_processor-0.1.5.dist-info/METADATA
similarity_processor-0.1.5.dist-info/WHEEL
similarity_processor-0.1.5.dist-info/top_level.txt
similarity_processor-0.1.5.dist-info/RECORD
