Metadata-Version: 2.1
Name: similarity-processor
Version: 0.1.5
Summary: Text Similarity
Home-page: https://github.com/philips-software/TextSimilarityProcessor
Author: Brijesh
Author-email: brijesh.krishnank@philips.com
License: UNKNOWN
Platform: UNKNOWN
Classifier: Programming Language :: Python :: 3
Classifier: License :: OSI Approved :: MIT License
Classifier: Operating System :: OS Independent
Requires-Python: >=3.7
Requires-Dist: xlrd (==1.2.0)
Requires-Dist: xlsxwriter (==1.2.1)
Requires-Dist: pandas (==1.0.5)
Requires-Dist: scikit-learn (==0.23.1)
Requires-Dist: numpy (==1.18.5)
